{
  "airports": [
    {
      "id": "634e64abefa8fc83c5c9b49b",
      "name": "Oatfarm",
      "ident": "1990-08-08",
      "local_code": null,
      "region": "Wildwood",
      "type": "medium_airport",
      "country": "Malaysia"
    },
    {
      "id": "634e64ab9bf481e61c73c843",
      "name": "Satiance",
      "ident": "1988-03-31",
      "local_code": null,
      "region": "Tilden",
      "type": "big_airport",
      "country": "Yugoslavia"
    },
    {
      "id": "634e64abac68142e7ae52b29",
      "name": "Qaboos",
      "ident": "1990-06-30",
      "local_code": null,
      "region": "Rutherford",
      "type": "medium_airport",
      "country": "Senegal"
    },
    {
      "id": "634e64ab50c12ffd043cb24e",
      "name": "Hyplex",
      "ident": "1989-02-18",
      "local_code": null,
      "region": "Cherokee",
      "type": "small_airport",
      "country": "Tanzania"
    },
    {
      "id": "634e64ab701ea38a62d2a521",
      "name": "Uniworld",
      "ident": "1989-12-23",
      "local_code": null,
      "region": "Norwood",
      "type": "big_airport",
      "country": "Greece"
    },
    {
      "id": "634e64abdd2912982dfa2e77",
      "name": "Magnafone",
      "ident": "1989-12-16",
      "local_code": null,
      "region": "Valle",
      "type": "small_airport",
      "country": "Brunei Darussalam"
    },
    {
      "id": "634e64ab03981bf9605bb8ba",
      "name": "Corporana",
      "ident": "1994-07-24",
      "local_code": null,
      "region": "Berwind",
      "type": "small_airport",
      "country": "Romania"
    },
    {
      "id": "634e64abcfb88c77b880917e",
      "name": "Hivedom",
      "ident": "1990-11-01",
      "local_code": null,
      "region": "Wheatfields",
      "type": "medium_airport",
      "country": "Suriname"
    },
    {
      "id": "634e64abc9a1770a061cfceb",
      "name": "Enersave",
      "ident": "1994-06-08",
      "local_code": null,
      "region": "Canby",
      "type": "big_airport",
      "country": "France, Metropolitan"
    },
    {
      "id": "634e64ab216e5f53156831c8",
      "name": "Liquidoc",
      "ident": "1992-08-27",
      "local_code": null,
      "region": "Lumberton",
      "type": "big_airport",
      "country": "Ireland"
    },
    {
      "id": "634e64abcdc225517bc36a14",
      "name": "Limage",
      "ident": "1994-06-19",
      "local_code": null,
      "region": "Ogema",
      "type": "small_airport",
      "country": "United Arab Emirates"
    },
    {
      "id": "634e64ab1c364db857872b2c",
      "name": "Minga",
      "ident": "1990-01-30",
      "local_code": null,
      "region": "Rowe",
      "type": "small_airport",
      "country": "Norway"
    },
    {
      "id": "634e64abc89c36a6cf5e3df4",
      "name": "Straloy",
      "ident": "1990-06-10",
      "local_code": null,
      "region": "Tampico",
      "type": "small_airport",
      "country": "Macedonia"
    },
    {
      "id": "634e64ab747b2b4002859617",
      "name": "Extro",
      "ident": "1988-12-23",
      "local_code": null,
      "region": "Johnsonburg",
      "type": "medium_airport",
      "country": "Syria"
    },
    {
      "id": "634e64abce3cf1f49d26ac52",
      "name": "Exerta",
      "ident": "1989-12-08",
      "local_code": null,
      "region": "Makena",
      "type": "big_airport",
      "country": "S. Georgia and S. Sandwich Isls."
    },
    {
      "id": "634e64abded3f1447e74c600",
      "name": "Avenetro",
      "ident": "1992-07-22",
      "local_code": null,
      "region": "Allentown",
      "type": "big_airport",
      "country": "Honduras"
    },
    {
      "id": "634e64abdb9573e1aa882fab",
      "name": "Lingoage",
      "ident": "1994-07-23",
      "local_code": null,
      "region": "Sedley",
      "type": "small_airport",
      "country": "Jordan"
    },
    {
      "id": "634e64ab7d4e1e02db0b6342",
      "name": "Endicil",
      "ident": "1991-10-22",
      "local_code": null,
      "region": "Alden",
      "type": "big_airport",
      "country": "Malta"
    },
    {
      "id": "634e64abbb3a910e4496466e",
      "name": "Accuprint",
      "ident": "1988-09-20",
      "local_code": null,
      "region": "Watchtower",
      "type": "small_airport",
      "country": "Korea (North)"
    },
    {
      "id": "634e64abf93a5b5f71666a9e",
      "name": "Kozgene",
      "ident": "1990-04-12",
      "local_code": null,
      "region": "Grayhawk",
      "type": "medium_airport",
      "country": "Montserrat"
    },
    {
      "id": "634e64abb9b0181bbe54bda0",
      "name": "Isotronic",
      "ident": "1988-10-10",
      "local_code": null,
      "region": "Kenwood",
      "type": "big_airport",
      "country": "Austria"
    },
    {
      "id": "634e64ab7f054d83f339ef5e",
      "name": "Virva",
      "ident": "1994-01-15",
      "local_code": null,
      "region": "Bourg",
      "type": "big_airport",
      "country": "Angola"
    },
    {
      "id": "634e64ab8fe446e912945165",
      "name": "Myopium",
      "ident": "1990-03-18",
      "local_code": null,
      "region": "Groveville",
      "type": "small_airport",
      "country": "Singapore"
    },
    {
      "id": "634e64ab7e4d6d5c0e725d1b",
      "name": "Buzzness",
      "ident": "1988-07-24",
      "local_code": null,
      "region": "Kenvil",
      "type": "big_airport",
      "country": "Slovak Republic"
    },
    {
      "id": "634e64ab49fc5a8f86f421a3",
      "name": "Isologia",
      "ident": "1992-12-12",
      "local_code": null,
      "region": "Tyhee",
      "type": "big_airport",
      "country": "Kyrgyzstan"
    },
    {
      "id": "634e64ab61bffd0b50516947",
      "name": "Uncorp",
      "ident": "1992-06-11",
      "local_code": null,
      "region": "Barrelville",
      "type": "medium_airport",
      "country": "Egypt"
    },
    {
      "id": "634e64abbc30f0816fe7304a",
      "name": "Medicroix",
      "ident": "1991-11-10",
      "local_code": null,
      "region": "Fulford",
      "type": "small_airport",
      "country": "Cyprus"
    },
    {
      "id": "634e64ab1edc25e0535b9e99",
      "name": "Buzzworks",
      "ident": "1989-12-22",
      "local_code": null,
      "region": "Stagecoach",
      "type": "medium_airport",
      "country": "Thailand"
    },
    {
      "id": "634e64ab87e2b5b3381f5542",
      "name": "Magneato",
      "ident": "1994-10-10",
      "local_code": null,
      "region": "Diaperville",
      "type": "medium_airport",
      "country": "Bulgaria"
    },
    {
      "id": "634e64ab0ca34277997179d1",
      "name": "Liquicom",
      "ident": "1994-03-25",
      "local_code": null,
      "region": "Blackgum",
      "type": "medium_airport",
      "country": "Tuvalu"
    },
    {
      "id": "634e64ab32abc51741eecf6b",
      "name": "Signity",
      "ident": "1993-08-11",
      "local_code": null,
      "region": "Villarreal",
      "type": "medium_airport",
      "country": "Equatorial Guinea"
    },
    {
      "id": "634e64ab88fbc9fc1b96eda5",
      "name": "Prosely",
      "ident": "1993-08-26",
      "local_code": null,
      "region": "Lynn",
      "type": "medium_airport",
      "country": "Tokelau"
    },
    {
      "id": "634e64abe55868863e494020",
      "name": "Biolive",
      "ident": "1991-05-24",
      "local_code": null,
      "region": "Edinburg",
      "type": "small_airport",
      "country": "Norfolk Island"
    },
    {
      "id": "634e64ab3f18e3489aefad3e",
      "name": "Schoolio",
      "ident": "1988-08-12",
      "local_code": null,
      "region": "Balm",
      "type": "big_airport",
      "country": "Algeria"
    },
    {
      "id": "634e64abcdf3d8e92813f6bc",
      "name": "Geekko",
      "ident": "1993-07-03",
      "local_code": null,
      "region": "Bennett",
      "type": "medium_airport",
      "country": "Portugal"
    },
    {
      "id": "634e64ab717589486ba302cf",
      "name": "Zidant",
      "ident": "1989-09-06",
      "local_code": null,
      "region": "Layhill",
      "type": "big_airport",
      "country": "Uganda"
    },
    {
      "id": "634e64ab986d5b829565294c",
      "name": "Plutorque",
      "ident": "1994-01-17",
      "local_code": null,
      "region": "Riner",
      "type": "small_airport",
      "country": "Netherlands Antilles"
    },
    {
      "id": "634e64ab9927a6d14a544623",
      "name": "Billmed",
      "ident": "1989-02-26",
      "local_code": null,
      "region": "Durham",
      "type": "medium_airport",
      "country": "Saudi Arabia"
    },
    {
      "id": "634e64ab6257c5ab8a36f11d",
      "name": "Aquasure",
      "ident": "1993-12-28",
      "local_code": null,
      "region": "Indio",
      "type": "big_airport",
      "country": "Bahamas"
    },
    {
      "id": "634e64ab772229ff579541be",
      "name": "Deminimum",
      "ident": "1990-09-24",
      "local_code": null,
      "region": "Sattley",
      "type": "big_airport",
      "country": "Argentina"
    },
    {
      "id": "634e64ab702617a8dab58031",
      "name": "Portico",
      "ident": "1988-08-02",
      "local_code": null,
      "region": "Loretto",
      "type": "medium_airport",
      "country": "Eritrea"
    },
    {
      "id": "634e64ab5a61a4bb448bea48",
      "name": "Comvoy",
      "ident": "1991-07-09",
      "local_code": null,
      "region": "Hickory",
      "type": "small_airport",
      "country": "Qatar"
    },
    {
      "id": "634e64ab500ffd7b5e1f5efb",
      "name": "Insuresys",
      "ident": "1993-12-15",
      "local_code": null,
      "region": "Summertown",
      "type": "small_airport",
      "country": "Finland"
    },
    {
      "id": "634e64abc1d8ecd2ebf3acfa",
      "name": "Qnekt",
      "ident": "1991-06-09",
      "local_code": null,
      "region": "Enlow",
      "type": "big_airport",
      "country": "Zimbabwe"
    },
    {
      "id": "634e64ab47360e02c632d590",
      "name": "Momentia",
      "ident": "1990-01-09",
      "local_code": null,
      "region": "Orick",
      "type": "small_airport",
      "country": "Kiribati"
    },
    {
      "id": "634e64ab8ee2c857f0c9c7bf",
      "name": "Orboid",
      "ident": "1993-07-02",
      "local_code": null,
      "region": "Sexton",
      "type": "small_airport",
      "country": "Afghanistan"
    },
    {
      "id": "634e64abdd16aabb4be6aa3c",
      "name": "Sultrax",
      "ident": "1990-07-03",
      "local_code": null,
      "region": "Duryea",
      "type": "small_airport",
      "country": "Bolivia"
    },
    {
      "id": "634e64abfb0163aeb1e4442e",
      "name": "Zuvy",
      "ident": "1991-10-07",
      "local_code": null,
      "region": "Coral",
      "type": "small_airport",
      "country": "Bangladesh"
    },
    {
      "id": "634e64abad69c67e8394f4ae",
      "name": "Phuel",
      "ident": "1988-06-26",
      "local_code": null,
      "region": "Tibbie",
      "type": "small_airport",
      "country": "Oman"
    },
    {
      "id": "634e64ab36ef0f1d6cf4147a",
      "name": "Quantalia",
      "ident": "1988-09-08",
      "local_code": null,
      "region": "Delwood",
      "type": "small_airport",
      "country": "Spain"
    },
    {
      "id": "634e64ab856f12db40b87a7f",
      "name": "Ronelon",
      "ident": "1991-10-29",
      "local_code": null,
      "region": "Marne",
      "type": "small_airport",
      "country": "Micronesia"
    },
    {
      "id": "634e64abcfbc69480dd27d6d",
      "name": "Polaria",
      "ident": "1991-07-16",
      "local_code": null,
      "region": "Yorklyn",
      "type": "big_airport",
      "country": "Iraq"
    },
    {
      "id": "634e64abdd53ba353cd6d7d9",
      "name": "Geekology",
      "ident": "1992-07-28",
      "local_code": null,
      "region": "Motley",
      "type": "medium_airport",
      "country": "Virgin Islands (US)"
    },
    {
      "id": "634e64abaadd2441b2be274e",
      "name": "Zaggles",
      "ident": "1993-02-28",
      "local_code": null,
      "region": "Rockhill",
      "type": "medium_airport",
      "country": "Swaziland"
    },
    {
      "id": "634e64abdb33b491146adeeb",
      "name": "Gynk",
      "ident": "1994-12-20",
      "local_code": null,
      "region": "Tooleville",
      "type": "small_airport",
      "country": "Monaco"
    },
    {
      "id": "634e64ab71f7f7f81c58f865",
      "name": "Maxemia",
      "ident": "1990-04-29",
      "local_code": null,
      "region": "Vincent",
      "type": "medium_airport",
      "country": "United States"
    },
    {
      "id": "634e64abe76e508dd0a890c9",
      "name": "Elita",
      "ident": "1994-10-11",
      "local_code": null,
      "region": "Allamuchy",
      "type": "medium_airport",
      "country": "Turkmenistan"
    },
    {
      "id": "634e64ab1d22d663313f1a9f",
      "name": "Adornica",
      "ident": "1994-10-02",
      "local_code": null,
      "region": "Stollings",
      "type": "small_airport",
      "country": "Saint Vincent and The Grenadines"
    },
    {
      "id": "634e64ab05245647cc007c7c",
      "name": "Suretech",
      "ident": "1989-02-09",
      "local_code": null,
      "region": "Nogal",
      "type": "big_airport",
      "country": "Turks and Caicos Islands"
    },
    {
      "id": "634e64ab66c042697b0508c1",
      "name": "Songlines",
      "ident": "1988-01-02",
      "local_code": null,
      "region": "Darlington",
      "type": "big_airport",
      "country": "Cape Verde"
    },
    {
      "id": "634e64ab27f5a5cc5762e4dd",
      "name": "Firewax",
      "ident": "1988-05-13",
      "local_code": null,
      "region": "Bynum",
      "type": "medium_airport",
      "country": "Virgin Islands (British)"
    },
    {
      "id": "634e64abd3cc9d481fce89c8",
      "name": "Sentia",
      "ident": "1990-05-18",
      "local_code": null,
      "region": "Smock",
      "type": "big_airport",
      "country": "Reunion"
    },
    {
      "id": "634e64ab5baa7067222027fc",
      "name": "Enthaze",
      "ident": "1994-02-16",
      "local_code": null,
      "region": "Floriston",
      "type": "big_airport",
      "country": "American Samoa"
    },
    {
      "id": "634e64ab041ebca42a16d73c",
      "name": "Zoxy",
      "ident": "1988-02-28",
      "local_code": null,
      "region": "Hoagland",
      "type": "small_airport",
      "country": "Lesotho"
    },
    {
      "id": "634e64ab5a05b6b7a8de1f04",
      "name": "Grok",
      "ident": "1988-09-07",
      "local_code": null,
      "region": "Caroline",
      "type": "small_airport",
      "country": "Libya"
    },
    {
      "id": "634e64abe4ace0ed1f2ad499",
      "name": "Ronbert",
      "ident": "1991-03-11",
      "local_code": null,
      "region": "Richville",
      "type": "small_airport",
      "country": "South Africa"
    },
    {
      "id": "634e64abdd739acc2e0800e1",
      "name": "Eventix",
      "ident": "1993-03-18",
      "local_code": null,
      "region": "Shasta",
      "type": "small_airport",
      "country": "Israel"
    },
    {
      "id": "634e64ab24be8bdfcbd7de3e",
      "name": "Veraq",
      "ident": "1991-06-15",
      "local_code": null,
      "region": "Rosedale",
      "type": "small_airport",
      "country": "Antigua and Barbuda"
    },
    {
      "id": "634e64ab113cd0160fe1794f",
      "name": "Permadyne",
      "ident": "1990-04-12",
      "local_code": null,
      "region": "Roy",
      "type": "small_airport",
      "country": "Dominica"
    },
    {
      "id": "634e64ab8738dff089b1f330",
      "name": "Aquacine",
      "ident": "1991-03-14",
      "local_code": null,
      "region": "Faxon",
      "type": "medium_airport",
      "country": "Zambia"
    },
    {
      "id": "634e64abdee997f4db8a9ae5",
      "name": "Goko",
      "ident": "1992-09-17",
      "local_code": null,
      "region": "Lewis",
      "type": "small_airport",
      "country": "Wallis and Futuna Islands"
    },
    {
      "id": "634e64ab9ed95c4d525ed90d",
      "name": "Neurocell",
      "ident": "1989-08-12",
      "local_code": null,
      "region": "Calpine",
      "type": "medium_airport",
      "country": "Netherlands"
    },
    {
      "id": "634e64ab13397cd7e46142e4",
      "name": "Duflex",
      "ident": "1990-02-11",
      "local_code": null,
      "region": "Glidden",
      "type": "small_airport",
      "country": "Albania"
    },
    {
      "id": "634e64ab3d152e12e6e6260d",
      "name": "Jamnation",
      "ident": "1988-02-27",
      "local_code": null,
      "region": "Fannett",
      "type": "big_airport",
      "country": "France"
    },
    {
      "id": "634e64ab62b26d7fd0d00cf9",
      "name": "Plasmos",
      "ident": "1994-11-07",
      "local_code": null,
      "region": "Bath",
      "type": "small_airport",
      "country": "Trinidad and Tobago"
    },
    {
      "id": "634e64ab306d552f916b75b6",
      "name": "Ontagene",
      "ident": "1994-04-15",
      "local_code": null,
      "region": "Ahwahnee",
      "type": "big_airport",
      "country": "San Marino"
    },
    {
      "id": "634e64ab5eb01fab04e91d88",
      "name": "Kenegy",
      "ident": "1989-03-11",
      "local_code": null,
      "region": "Hall",
      "type": "big_airport",
      "country": "Paraguay"
    },
    {
      "id": "634e64ab4a34ba5ff65d3fc1",
      "name": "Extragen",
      "ident": "1991-11-06",
      "local_code": null,
      "region": "Ironton",
      "type": "big_airport",
      "country": "Puerto Rico"
    },
    {
      "id": "634e64abccaa543dfff2f0f6",
      "name": "Injoy",
      "ident": "1992-08-01",
      "local_code": null,
      "region": "Como",
      "type": "big_airport",
      "country": "Latvia"
    },
    {
      "id": "634e64ab93acfdd3747e6912",
      "name": "Ultrimax",
      "ident": "1993-03-20",
      "local_code": null,
      "region": "Nicut",
      "type": "small_airport",
      "country": "Uzbekistan"
    },
    {
      "id": "634e64ab5625ad67101af125",
      "name": "Jumpstack",
      "ident": "1994-11-06",
      "local_code": null,
      "region": "Cresaptown",
      "type": "medium_airport",
      "country": "French Southern Territories"
    },
    {
      "id": "634e64ab0eaa93f6b6b614eb",
      "name": "Vidto",
      "ident": "1989-03-23",
      "local_code": null,
      "region": "Bodega",
      "type": "small_airport",
      "country": "Lebanon"
    },
    {
      "id": "634e64ab9bd4a5cdf0adeeb2",
      "name": "Exostream",
      "ident": "1992-05-13",
      "local_code": null,
      "region": "Chalfant",
      "type": "big_airport",
      "country": "Saint Lucia"
    },
    {
      "id": "634e64abbfb067368f222557",
      "name": "Namebox",
      "ident": "1993-01-12",
      "local_code": null,
      "region": "Sunriver",
      "type": "medium_airport",
      "country": "Andorra"
    },
    {
      "id": "634e64ab7f1895b69bb147f3",
      "name": "Bluegrain",
      "ident": "1992-08-19",
      "local_code": null,
      "region": "Southview",
      "type": "big_airport",
      "country": "Guadeloupe"
    },
    {
      "id": "634e64abe098512541c3128f",
      "name": "Marketoid",
      "ident": "1994-07-16",
      "local_code": null,
      "region": "Byrnedale",
      "type": "big_airport",
      "country": "Cambodia"
    },
    {
      "id": "634e64abfa2fc5ecfbfb374e",
      "name": "Entroflex",
      "ident": "1992-07-04",
      "local_code": null,
      "region": "Grill",
      "type": "small_airport",
      "country": "Sudan"
    },
    {
      "id": "634e64ab00a447adcc4f3cd2",
      "name": "Kyagoro",
      "ident": "1993-07-22",
      "local_code": null,
      "region": "Rosewood",
      "type": "big_airport",
      "country": "Zaire"
    }
  ]
}
